<?xml version="1.0" encoding="UTF-8"?>
<objects serializationModel="Studio.01.10.00">
    <object class="Platform" id="{52d96485-c18d-4579-9531-723deb81f34b}">
        <property name="hardwareType">
            <value>0</value>
        </property>
        <property name="name">
            <value>Desktop</value>
        </property>
        <property name="subDirectory">
            <value>Desktop</value>
        </property>
        <property name="speakerFormat">
            <value>1</value>
        </property>
    </object>
</objects>
